serial_tool/__init__.py
serial_tool/serial.py
serial_tool-0.0.1.dist-info/LICENCE
serial_tool-0.0.1.dist-info/METADATA
serial_tool-0.0.1.dist-info/WHEEL
serial_tool-0.0.1.dist-info/entry_points.txt
serial_tool-0.0.1.dist-info/top_level.txt
serial_tool-0.0.1.dist-info/RECORD
