Metadata-Version: 2.1
Name: serial-tool
Version: 0.0.1
Summary: A serial tool
Home-page: https://github.com/zcq100/serial-tool
Author: zcq100
Author-email: zcq100@gmail.com
License: UNKNOWN
Platform: UNKNOWN
Classifier: Programming Language :: Python :: 3
Classifier: License :: OSI Approved :: MIT License
Classifier: Operating System :: OS Independent
Requires-Python: >=3.6
